riksbank/__init__.py
riksbank/riksbank.py
test/__init__.py
test/test_riksbank.py
riksbank-1.0.0.dist-info/LICENSE
riksbank-1.0.0.dist-info/METADATA
riksbank-1.0.0.dist-info/WHEEL
riksbank-1.0.0.dist-info/top_level.txt
riksbank-1.0.0.dist-info/RECORD
