Metadata-Version: 2.1
Name: riksbank
Version: 1.0.0
Summary: Access the API of the Swedish central bank (riksbanken)
Home-page: https://github.com/thpe/riksbank
Author: Thomas Petig
Author-email: thomas@petig.eu
Classifier: Programming Language :: Python :: 3
Classifier: License :: OSI Approved :: MIT License
Classifier: Operating System :: OS Independent
License-File: LICENSE
Requires-Dist: requests
Requires-Dist: pandas
